tasks.py
tvm/__init__.py
tvm/_ffi.cpython-310-x86_64-linux-gnu.so
tvm/arith.cpython-310-x86_64-linux-gnu.so
tvm/auto_scheduler.cpython-310-x86_64-linux-gnu.so
tvm/autotvm.cpython-310-x86_64-linux-gnu.so
tvm/contrib.cpython-310-x86_64-linux-gnu.so
tvm/driver.cpython-310-x86_64-linux-gnu.so
tvm/error.cpython-310-x86_64-linux-gnu.so
tvm/exec.cpython-310-x86_64-linux-gnu.so
tvm/generic.cpython-310-x86_64-linux-gnu.so
tvm/ir.cpython-310-x86_64-linux-gnu.so
tvm/micro.cpython-310-x86_64-linux-gnu.so
tvm/parser.cpython-310-x86_64-linux-gnu.so
tvm/rpc.cpython-310-x86_64-linux-gnu.so
tvm/runtime.cpython-310-x86_64-linux-gnu.so
tvm/script.cpython-310-x86_64-linux-gnu.so
tvm/support.cpython-310-x86_64-linux-gnu.so
tvm/target.cpython-310-x86_64-linux-gnu.so
tvm/te.cpython-310-x86_64-linux-gnu.so
tvm/testing.cpython-310-x86_64-linux-gnu.so
tvm/tir.cpython-310-x86_64-linux-gnu.so
tvm/topi.cpython-310-x86_64-linux-gnu.so
tvm/relay/__init__.py
tvm/relay/_build_module.cpython-310-x86_64-linux-gnu.so
tvm/relay/_ffi_api.cpython-310-x86_64-linux-gnu.so
tvm/relay/_make.cpython-310-x86_64-linux-gnu.so
tvm/relay/adt.cpython-310-x86_64-linux-gnu.so
tvm/relay/analysis.cpython-310-x86_64-linux-gnu.so
tvm/relay/backend.cpython-310-x86_64-linux-gnu.so
tvm/relay/base.cpython-310-x86_64-linux-gnu.so
tvm/relay/build_module.cpython-310-x86_64-linux-gnu.so
tvm/relay/data_dep_optimization.cpython-310-x86_64-linux-gnu.so
tvm/relay/dataflow_pattern.cpython-310-x86_64-linux-gnu.so
tvm/relay/debug.cpython-310-x86_64-linux-gnu.so
tvm/relay/expr.cpython-310-x86_64-linux-gnu.so
tvm/relay/expr_functor.cpython-310-x86_64-linux-gnu.so
tvm/relay/frontend.cpython-310-x86_64-linux-gnu.so
tvm/relay/function.cpython-310-x86_64-linux-gnu.so
tvm/relay/loops.cpython-310-x86_64-linux-gnu.so
tvm/relay/op.cpython-310-x86_64-linux-gnu.so
tvm/relay/param_dict.cpython-310-x86_64-linux-gnu.so
tvm/relay/prelude.cpython-310-x86_64-linux-gnu.so
tvm/relay/qnn.cpython-310-x86_64-linux-gnu.so
xm_gnpu_v100-0.0.5.dist-info/METADATA
xm_gnpu_v100-0.0.5.dist-info/WHEEL
xm_gnpu_v100-0.0.5.dist-info/licenses/LICENSE
xm_gnpu_v100-0.0.5.dist-info/RECORD
