Metadata-Version: 2.1
Name: xm-gnpu-v100
Version: 0.0.5
Summary: 雄迈工具链
Author-email: liuxinwei <liuxinwei@xmsilicon.cn>
License-Expression: MIT
License-File: LICENSE
Keywords: tvm,vta,xm-gnpu-v100
Classifier: Development Status :: 4 - Beta
Classifier: Programming Language :: Python
Classifier: Programming Language :: Python :: 3.8
Classifier: Programming Language :: Python :: 3.9
Classifier: Programming Language :: Python :: 3.10
Classifier: Programming Language :: Python :: 3.11
Classifier: Programming Language :: Python :: Implementation :: CPython
Classifier: Programming Language :: Python :: Implementation :: PyPy
Requires-Python: >=3.8
Requires-Dist: scipy
